{"id":"agent-visual-1760971159","agent_id":"retrospective","workspace_id":"contextpilot","user_id":"system","is_system_proposal":true,"title":"🤖 Agent Proposal - Visual Test","description":"This proposal was created by an AGENT. Notice the robot icon (🤖) in the UI!","diff":null,"proposed_changes":[{"file_path":"docs/agent_agent-visual-1760971159.md","change_type":"create","description":"Agent-created file","before":null,"after":"# 🤖 Agent Proposal\n\nCreated by AI agent","diff":null}],"status":"approved","created_at":"2025-10-20T14:39:19.788181Z","updated_at":null,"approved_at":"2025-10-20T14:43:28.864000Z","rejected_at":null,"rejection_reason":null,"ai_review":null}